{"code":"opblaaszwembaden","name":{"nl":"Opblaaszwembaden","en":"Inflatable pools","de":"Aufblasbare Pools"},"slug":{"nl":"/c/opblaaszwembaden","en":"/en/c/inflatable-pools","de":"/de/c/aufblasbare-pools"},"googleCategory":null,"parentCategory":"zwembaden","indexable":true,"active":true,"icon":null,"facets":[{"code":"diameter-length","name":{"nl":"Diameter / Lengte","en":"Diameter/Length","de":"Durchmesser / Länge"},"postfix":null,"variable":true,"facet":true},{"code":"depth-bath","name":{"nl":"Diepte bad","en":"Depth bath","de":"Tiefere Badewanne"},"postfix":null,"variable":true,"facet":true}],"createdAt":1651366831538,"updatedAt":1653680449216}