{"ean":"8717249193913","name":{"nl":"uitbreiding kaartspel Dominion: Welvaart (NL)","en":"dominion expansion card game: Prosperity (NL)","de":"dominion Erweiterung Kartenspiel: Wohlstand (NL)"},"slug":{"nl":"/c/kaartspellen/999-games/8717249193913/uitbreiding-kaartspel-dominion-welvaart-nl","en":"/en/c/card-games/999-games/8717249193913/dominion-expansion-card-game-prosperity-nl","de":"/de/c/kartenspiele/999-games/8717249193913/dominion-erweiterung-kartenspiel-wohlstand-nl"},"description":{"nl":"999 Games Dominion: Welvaart kaartspel\r\n\r\nAh, geld. Er gaat niets boven het geluid van klinkende munten in je hand. Je prefereert het zeker boven het geluid van munten in andermans handen, of boven het geluid van munten in een kluis waar niemand bij komt zonder eerst zijn status te verhogen. Status verhogen, dat ligt achter je. Het leven is goed voor je geweest. tien jaar geleden werkte je nog met een simpele strooien hoed op je hoofd op je eigen akkers. Tegenwoordig strekt je koninkrijk zich uit van zee tot zee en is jouw strooien hoed de grootstedie de wereld ooit heft gezien. Je bezit ook de kleinste hond ter wereld en een levensgroot standbeeld van jezelf, gemaakt van baklava. Natuurlijk kun je met geld geen geluk kopen, maar wel jaloezie, woede en ook een soort van leeg gevoel. Je hebt nog steeds problemen – storende buren die moeten worden verslagen. Maar deze keer doe je dat in stijl. Een beetje geld en een paar kleine landgoederen, meer heb je aan het begin van het spel niet. Maar de wereld staat voor je open, want je mag een koninkrijk opbouwen. Eindelijk kun je de vruchten van al je arbeid plukken.\r\n\r\nDeze uitbreiding op Dominion bevat 25 nieuwe koninkrijkkaarten en twee nieuwe standaard kaarten, waarmee de spelers verder kunnen bouwen dan Goud en Provincies. Het centrale thema is rijkdom; er zijn geldkaarten met actiemogelijkheden, kaarten die interactie met geldkaarten hebben en dure, krachtige kaarten.\r\n\r\nSpecificaties:\r\nGeslacht: unisex\r\nKleur: multicolor\r\nMateriaal: karton\r\nAfmetingen: 29,7 x 29,7 x 7,2 cm (LxBxD)\r\nTaal: Nederlands\r\nAantal spelers: 2 tot 4 spelers\r\nSpeelduur: 30 minuten\r\nLeeftijd: vanaf 10 jaar\r\n\r\nInhoud:\r\n8 Tableaus voor overwinningspuntenfiches\r\n1 Handelsroutetableau\r\n16 Overwinningspuntenfiches(1)\r\n15 Overwinningspuntenfiches(5)\r\n8 Muntenfiches\r\n24 Standaard kaarten\r\n25 Locatiekaarten\r\n1 Blanco kaart\r\n250 Koninkrijkkaarten","en":"999 Games Dominion: Prosperity card game\r\n\r\nAh, money. Nothing beats the sound of clinking coins in your hand. You certainly prefer it to the sound of coins in other people's hands, or to the sound of coins in a vault that no one can get to without first raising their status. Raising status, that's behind you. Life has been good to you. ten years ago, you worked your own fields with a simple straw hat on your head. Today your kingdom stretches from sea to sea and your straw hat is the biggest city the world has ever seen. You also own the smallest dog in the world and a life-size statue of yourself made of baklava. Of course, money can't buy happiness, but it can buy jealousy, anger, and a sense of emptiness. You still have problems - disruptive neighbors who need to be defeated. But this time you do it in style. A little money and a few small estates, that's all you have at the beginning of the game. But the world is open to you, because you get to build a kingdom. Finally, you can reap the rewards of all your labor.\r\n\r\nThis expansion to Dominion contains 25 new kingdom cards and two new standard cards that allow players to build beyond Gold and Provinces. The central theme is wealth; there are money cards with action possibilities, cards that interact with money cards and expensive, powerful cards.\r\n\r\nSpecifications:\r\nGender: unisex\r\nColour: multicoloured\r\nMaterial: cardboard\r\nDimensions: 29,7 x 29,7 x 7,2 cm (LxWxD)\r\nLanguage: Dutch\r\nNumber of players: 2 to 4 players\r\nPlaying time: 30 minutes\r\nAge: 10 years and up\r\n\r\nContents:\r\n8 Tableaus for victory point tokens\r\n1 trading route tableau\r\n16 Victory Point chits(1)\r\n15 Victory Point tokens(5)\r\n8 Coin tiles\r\n24 Standard cards\r\n25 Location cards\r\n1 Blank card\r\n250 Kingdom cards","de":"999 Games Dominion: Wohlstandskartenspiel\r\n\r\nAh, Geld. Es gibt nichts Besseres als das Geräusch klirrender Münzen in Ihrer Hand. Sie ziehen es sicherlich dem Klang von Münzen in den Händen anderer vor, oder dem Klang von Münzen in einem Tresor, an den niemand herankommt, ohne vorher seinen Status zu erhöhen. Statuserhöhung, das liegt hinter Ihnen. Das Leben hat es gut mit Ihnen gemeint: Vor zehn Jahren bearbeiteten Sie Ihre eigenen Felder mit einem einfachen Strohhut auf dem Kopf. Heute erstreckt sich dein Königreich von Meer zu Meer, und dein Strohhut ist die größte Stadt, die die Welt je gesehen hat. Sie besitzen auch den kleinsten Hund der Welt und eine lebensgroße Statue von sich selbst aus Baklava. Natürlich kann man mit Geld kein Glück kaufen, aber man kann damit Eifersucht, Wut und auch eine Art von Leere kaufen. Sie haben immer noch Probleme - lästige Nachbarn, die besiegt werden müssen. Aber dieses Mal machen Sie es mit Stil. Ein bisschen Geld und ein paar kleine Ländereien, das ist alles, was du zu Beginn des Spiels hast. Aber die Welt steht dir offen, denn du kannst ein Reich errichten. Endlich können Sie die Früchte Ihrer Arbeit ernten.\r\n\r\nDiese Erweiterung zu Dominion enthält 25 neue Königreichkarten und zwei neue Standardkarten, die es den Spielern ermöglichen, über Gold und Provinzen hinaus zu bauen. Das zentrale Thema ist Reichtum; es gibt Geldkarten mit Aktionsmöglichkeiten, Karten, die mit Geldkarten interagieren und teure, mächtige Karten.\r\n\r\nSpezifikationen:\r\nGeschlecht: unisex\r\nFarbe: mehrfarbig\r\nMaterial: Karton\r\nAbmessungen: 29,7 x 29,7 x 7,2 cm (LxBxT)\r\nSprache: Niederländisch\r\nAnzahl der Spieler: 2 bis 4 Spieler\r\nSpieldauer: 30 Minuten\r\nAlter: 10 Jahre und älter\r\n\r\nInhalt\r\n8 Tableaus für Siegpunktplättchen\r\n1 Tableau der Handelsroute\r\n16 Siegpunktchips(1)\r\n15 Siegpunktplättchen(5)\r\n8 Münzplättchen\r\n24 Standard-Karten\r\n25 Standortkarten\r\n1 leere Karte\r\n250 Königreichskarten"},"brand":{"name":"999 Games","description":null,"active":true,"logo":null,"createdAt":1651368112597,"updatedAt":1651368112597},"vendorPrice":32.51,"sellingPrice":64.95,"catalogPrice":60.257999999999996,"sellingPriceMin":null,"active":true,"featured":false,"hasVariants":false,"reviewPending":true,"categories":[{"code":"kaartspellen","name":{"nl":"Kaartspellen","en":"Card games","de":"Kartenspiele"},"slug":{"nl":"/c/kaartspellen","en":"/en/c/card-games","de":"/de/c/kartenspiele"},"googleCategory":null,"parentCategory":"spellen","indexable":true,"active":true,"icon":null,"facets":null,"createdAt":1651366806970,"updatedAt":1651366806970}],"variantOptions":null,"stock":[{"id":"626de0be4df724026bc206a1","location":"TWM","quantity":13,"updatedAt":1651368126721}],"images":[{"url":"https://www.twm-bv.com/producten/original/999_games_kaartspel_dominion_welvaart_467951_1601385520.jpg"},{"url":"https://www.twm-bv.com/producten/original/999_games_kaartspel_dominion_welvaart_2_467951_1601385520.jpg"}],"attributes":[{"type":{"code":"target-audience","name":{"nl":"Doelgroep","en":"Target audience","de":"Zielgruppe"},"postfix":null,"variable":true,"facet":true},"value":{"nl":"Kinderen, Volwassenen","en":"Children, Adult","de":"Kind, Erwachsene"},"variants":null,"active":true},{"type":{"code":"battery-type","name":{"nl":"Type batterij","en":"Battery type","de":"Batterietyp"},"postfix":null,"variable":true,"facet":true},"value":{"nl":"Geen batterijen","en":"No batteries","de":"Keine Batterien"},"variants":null,"active":true},{"type":{"code":"mobile-data-connection-possible","name":{"nl":"Mobiele data verbinding mogelijk","en":"Mobile data connection possible","de":"Mobile Datenverbindung verfügbar"},"postfix":null,"variable":true,"facet":true},"value":{"nl":"Niet van toepassing","en":"Does not apply","de":"Gilt nicht"},"variants":null,"active":true},{"type":{"code":"running-time","name":{"nl":"Spelduur","en":"Running time","de":"Spieldauer"},"postfix":null,"variable":true,"facet":true},"value":{"nl":"30-59 Minuten","en":"30-59 Minutes","de":"30-59 Minuten"},"variants":null,"active":true},{"type":{"code":"gender","name":{"nl":"Geslacht","en":"Gender","de":"Geschlecht"},"postfix":null,"variable":true,"facet":true},"value":{"nl":"Unisex","en":"Unisex","de":"Unisex"},"variants":null,"active":true},{"type":{"code":"colour","name":{"nl":"Kleur","en":"Colour","de":"Farbe"},"postfix":null,"variable":true,"facet":true},"value":{"nl":"Multicolor","en":"Multicolor","de":"Multicolor"},"variants":null,"active":true},{"type":{"code":"app-works-on-operating-system","name":{"nl":"App werkt op besturingssysteem","en":"App works on operating system","de":"App funktioniert auf Betriebssystem"},"postfix":null,"variable":true,"facet":true},"value":{"nl":"Niet van toepassing","en":"Does not apply","de":"Gilt nicht"},"variants":null,"active":true},{"type":{"code":"number-of-players","name":{"nl":"Aantal spelers","en":"Number of Players","de":"Anzahl Spieler"},"postfix":null,"variable":true,"facet":true},"value":{"nl":"2-4 Spelers","en":"2-4 Players","de":"2-4 Spieler"},"variants":null,"active":true},{"type":{"code":"app-required-for-full-functionality","name":{"nl":"App vereist voor volledige functionaliteit","en":"App required for full functionality","de":"App benötigt für die volle Funktionalität"},"postfix":null,"variable":true,"facet":true},"value":{"nl":"Nee","en":"No","de":"Nein"},"variants":null,"active":true},{"type":{"code":"paid-services-required","name":{"nl":"Betaalde diensten vereist","en":"Paid services required","de":"Erfordern bezahlte Dienstleistungen"},"postfix":null,"variable":true,"facet":true},"value":{"nl":"Niet van toepassing","en":"Does not apply","de":"Gilt nicht"},"variants":null,"active":true},{"type":{"code":"language","name":{"nl":"Taal","en":"Language","de":"Sprache"},"postfix":null,"variable":true,"facet":true},"value":{"nl":"Nederlands","en":"Dutch","de":"Niederländisch"},"variants":null,"active":true},{"type":{"code":"language-game","name":{"nl":"Taal spel","en":"Language game","de":"Sprache Spiel"},"postfix":null,"variable":true,"facet":true},"value":{"nl":"Nederlands","en":"Dutch","de":"Niederländisch"},"variants":null,"active":true},{"type":{"code":"manual-language","name":{"nl":"Taal handleiding","en":"Manual language","de":"Manuelle Sprache"},"postfix":null,"variable":true,"facet":true},"value":{"nl":"Geen taal, Universeel","en":"Keine Sprache, Universal","de":"Nicht zutreffend, Universal"},"variants":null,"active":true},{"type":{"code":"bluetooth-required","name":{"nl":"Bluetooth vereist","en":"Bluetooth required","de":"Bluetooth erforderlich"},"postfix":null,"variable":true,"facet":true},"value":{"nl":"Niet van toepassing","en":"Does not apply","de":"Gilt nicht"},"variants":null,"active":true},{"type":{"code":"age","name":{"nl":"Leeftijd","en":"Age","de":"Alter"},"postfix":null,"variable":true,"facet":true},"value":{"nl":"10-12 Jaar, Vanaf 12 Jaar","en":"10-12 Years, From 12 Years","de":"10-12 Jahr, Ab 12 Jahr"},"variants":null,"active":true},{"type":{"code":"compatible-to-connect","name":{"nl":"Compatibel met","en":"Compatible to connect","de":"Kompatibel mit"},"postfix":null,"variable":true,"facet":true},"value":{"nl":"Niet van toepassing","en":"Does not apply","de":"Gilt nicht"},"variants":null,"active":true},{"type":{"code":"wifi-required","name":{"nl":"Wifi vereist","en":"WiFi required","de":"Benötigt wifi"},"postfix":null,"variable":true,"facet":true},"value":{"nl":"Niet van toepassing","en":"Does not apply","de":"Gilt nicht"},"variants":null,"active":true},{"type":{"code":"sharing-user-data-required","name":{"nl":"Delen van gebruikersgegevens vereist","en":"Sharing user data required","de":"Gemeinsame Nutzung von Benutzerdaten erforderlich"},"postfix":null,"variable":true,"facet":true},"value":{"nl":"Niet van toepassing","en":"Does not apply","de":"Gilt nicht"},"variants":null,"active":true},{"type":{"code":"product-language","name":{"nl":"Producttaal","en":"Product language","de":"Produktsprache"},"postfix":null,"variable":true,"facet":true},"value":{"nl":"Universeel","en":"Universal","de":"Universal"},"variants":null,"active":true},{"type":{"code":"material","name":{"nl":"Materiaal","en":"Material","de":"Material"},"postfix":null,"variable":true,"facet":true},"value":{"nl":"Karton","en":"Cardboard","de":"Karton"},"variants":null,"active":true},{"type":{"code":"connects-independently-to-internet","name":{"nl":"Kan zelfstandig met internet verbinden","en":"Connects independently to internet","de":"Kann unabhängig mit dem Internet verbinden"},"postfix":null,"variable":true,"facet":true},"value":{"nl":"Nee","en":"No","de":"Nein"},"variants":null,"active":true},{"type":{"code":"game-type","name":{"nl":"Spelsoort","en":"Game type","de":"Spieltyp"},"postfix":null,"variable":true,"facet":true},"value":{"nl":"Speelkaarten","en":"Playing cards","de":"Kartenspielen"},"variants":null,"active":true},{"type":{"code":"support-with-updates","name":{"nl":"Ondersteuning met updates","en":"Support with updates","de":"Unterstützung bei Updates"},"postfix":null,"variable":true,"facet":true},"value":{"nl":"Niet van toepassing","en":"Does not apply","de":"Gilt nicht"},"variants":null,"active":true},{"type":{"code":"power-source-used","name":{"nl":"Voedingstype","en":"Power source used","de":"Verwendete Stromquelle"},"postfix":null,"variable":true,"facet":true},"value":{"nl":"Geen voedingstype","en":"No power supply type","de":"Kein Stromversorgungstyp"},"variants":null,"active":true},{"type":{"code":"known-characters","name":{"nl":"Bekende karakters","en":"Known characters","de":"Bekannte Charaktere"},"postfix":null,"variable":true,"facet":true},"value":{"nl":"Geen personage","en":"No character","de":"Kein Charakter"},"variants":null,"active":true},{"type":{"code":"game-edition","name":{"nl":"Speleditie","en":"Game edition","de":"Spieledition"},"postfix":null,"variable":true,"facet":true},"value":{"nl":"Uitbreiding","en":"Expansion","de":"Expansion"},"variants":null,"active":true}],"createdAt":1651368126720,"lastImportedAt":1653088380501,"updatedAt":1653088380501,"source":"TWM","sourceId":"467951","shippingSize":"S"}