[{"code":"lego-accessoires","name":{"nl":"LEGO-accessoires","en":"LEGO accessoires","de":"LEGO Accessoires"},"slug":{"nl":"/c/lego-accessoires","en":"/en/c/lego-accessoires","de":"/de/c/lego-accessoires"},"googleCategory":null,"parentCategory":"lego","indexable":true,"active":true,"icon":null,"facets":null,"createdAt":1651368132523,"updatedAt":1651368132523},{"code":"lego-classic","name":{"nl":"LEGO Classic","en":"LEGO Classic","de":"LEGO Classic"},"slug":{"nl":"/c/lego-classic","en":"/en/c/lego-classic","de":"/de/c/lego-classic"},"googleCategory":null,"parentCategory":"lego","indexable":true,"active":true,"icon":null,"facets":null,"createdAt":1651366910642,"updatedAt":1651366910642},{"code":"lego-opbergboxen","name":{"nl":"LEGO opbergboxen","en":"LEGO storage boxes","de":"LEGO Aufbewahrungsboxen"},"slug":{"nl":"/c/lego-opbergboxen","en":"/en/c/lego-storage-boxes","de":"/de/c/lego-aufbewahrungsboxen"},"googleCategory":null,"parentCategory":"lego","indexable":true,"active":true,"icon":null,"facets":null,"createdAt":1651366807106,"updatedAt":1651366807106},{"code":"lego-super-mario","name":{"nl":"LEGO Super Mario","en":"LEGO Super Mario","de":"LEGO Super Mario"},"slug":{"nl":"/c/lego-super-mario","en":"/en/c/lego-super-mario","de":"/de/c/lego-super-mario"},"googleCategory":null,"parentCategory":"lego","indexable":true,"active":true,"icon":null,"facets":null,"createdAt":1651368083784,"updatedAt":1651368083784}]