[{"code":"boxbumpers","name":{"nl":"Boxbumpers","en":"Boxbumpers","de":"Boxbumpers"},"slug":{"nl":"/c/boxbumpers","en":"/en/c/boxbumpers","de":"/de/c/boxbumpers"},"googleCategory":null,"parentCategory":"boxen","indexable":true,"active":true,"icon":null,"facets":null,"createdAt":1651369580917,"updatedAt":1651369580917},{"code":"boxen","name":{"nl":"Boxen","en":"Boxes","de":"Boxen"},"slug":{"nl":"/c/boxen","en":"/en/c/boxes","de":"/de/c/boxen"},"googleCategory":null,"parentCategory":"boxen","indexable":true,"active":true,"icon":null,"facets":null,"createdAt":1651369565335,"updatedAt":1651369565335}]